LICENSE
MANIFEST.in
README.md
setup.py
test/test_veering_census.py
veering/__init__.py
veering/basic_math.py
veering/branched_surface.py
veering/carried_surface.py
veering/drill.py
veering/edge_orientability.py
veering/fibered.py
veering/file_io.py
veering/flow_cycles.py
veering/fundamental_domain.py
veering/fundamental_group.py
veering/mutation.py
veering/pachner.py
veering/sage_tools.py
veering/snappy_tools.py
veering/taut.py
veering/taut_carried.py
veering/taut_euler_class.py
veering/taut_homology.py
veering/taut_polynomial.py
veering/taut_polytope.py
veering/test_suite.py
veering/transverse_taut.py
veering/veering_dehn_surgery.py
veering/veering_drill_midsurface_bdy.py
veering/veering_fan_excision.py
veering/veering_polynomial.py
veering/veering_tri.py
veering/z2_taut.py
veering/z_charge.py
veering.egg-info/PKG-INFO
veering.egg-info/SOURCES.txt
veering.egg-info/dependency_links.txt
veering.egg-info/requires.txt
veering.egg-info/top_level.txt
veering/data/mflds_which_fiber.txt
veering/data/veering_census.txt
veering/data/veering_census_with_data.txt
veering/data/veering_non_transverse_taut_examples.txt