Metadata-Version: 2.1
Name: veering
Version: 0.3
Summary: Taut and veering triangulations
Home-page: https://github.com/henryseg/Veering
Author: Anna Parlak, Henry Segerman, Saul Schleimer
Author-email: segerman@math.okstate.edu
License: UNKNOWN
Keywords: surfaces,manifolds,geometry,taut triangulation,veering triangulation
Platform: UNKNOWN
